Polygott/__init__.py
Polygott/setup.py
Polygott-0.0.1.dist-info/METADATA
Polygott-0.0.1.dist-info/WHEEL
Polygott-0.0.1.dist-info/top_level.txt
Polygott-0.0.1.dist-info/RECORD
