Metadata-Version: 2.1
Name: Polygott
Version: 0.0.1
Summary: run polygott in python
Home-page: https://repl.it/@Downey/Polygott-python
Author: Repl.it User
Author-email: xsumagravity@gmail.com
License: UNKNOWN
Platform: UNKNOWN
Classifier: Programming Language :: Python :: 3
Classifier: License :: OSI Approved :: MIT License
Classifier: Operating System :: MacOS
Requires-Python: >=3.6
